karrio/mappers/asendia/__init__.py
karrio/mappers/asendia/mapper.py
karrio/mappers/asendia/proxy.py
karrio/mappers/asendia/settings.py
karrio/plugins/asendia/__init__.py
karrio/providers/asendia/__init__.py
karrio/providers/asendia/error.py
karrio/providers/asendia/manifest.py
karrio/providers/asendia/tracking.py
karrio/providers/asendia/units.py
karrio/providers/asendia/utils.py
karrio/providers/asendia/shipment/__init__.py
karrio/providers/asendia/shipment/cancel.py
karrio/providers/asendia/shipment/create.py
karrio/schemas/asendia/__init__.py
karrio/schemas/asendia/auth_request.py
karrio/schemas/asendia/auth_response.py
karrio/schemas/asendia/error_response.py
karrio/schemas/asendia/manifest_request.py
karrio/schemas/asendia/manifest_response.py
karrio/schemas/asendia/shipment_cancel_request.py
karrio/schemas/asendia/shipment_cancel_response.py
karrio/schemas/asendia/shipment_request.py
karrio/schemas/asendia/shipment_response.py
karrio/schemas/asendia/tracking_request.py
karrio/schemas/asendia/tracking_response.py
karrio_asendia-2026.1.4.dist-info/METADATA
karrio_asendia-2026.1.4.dist-info/WHEEL
karrio_asendia-2026.1.4.dist-info/entry_points.txt
karrio_asendia-2026.1.4.dist-info/top_level.txt
karrio_asendia-2026.1.4.dist-info/RECORD
